[
  {
    "n": "Mercury",
    "p": 87.9691,
    "perr": 0.001,
    "b": "local"
  },
  {
    "n": "Venus",
    "p": 224.701,
    "perr": 0.001,
    "b": "local"
  },
  {
    "n": "Earth",
    "p": 365.256363004,
    "perr": 0.001,
    "b": "local"
  },
  {
    "n": "Mars",
    "p": 686.971,
    "perr": 0.001,
    "b": "local"
  },
  {
    "n": "Jupiter",
    "p": 4332.59,
    "perr": 0.001,
    "b": "local"
  },
  {
    "n": "Saturn",
    "p": 10759.22,
    "perr": 0.001,
    "b": "local"
  },
  {
    "n": "Uranus",
    "p": 30687.15,
    "perr": 0.001,
    "b": "local"
  },
  {
    "n": "Neptune",
    "p": 60190.03,
    "perr": 0.001,
    "b": "local"
  },
  {
    "n": "Pluto",
    "p": 90465,
    "perr": 0.001,
    "b": "local"
  },
  {
    "n": "11 Com b",
    "p": 326.03,
    "perr": 0.32,
    "b": "exo"
  },
  {
    "n": "11 Oph b",
    "p": 730000,
    "perr": 365000,
    "b": "exo"
  },
  {
    "n": "11 UMi b",
    "p": 516.22,
    "perr": 3.25,
    "b": "exo"
  },
  {
    "n": "14 And b",
    "p": 185.84,
    "perr": 0.23,
    "b": "exo"
  },
  {
    "n": "14 Her b",
    "p": 1773.4,
    "perr": 2.5,
    "b": "exo"
  },
  {
    "n": "16 Cyg B b",
    "p": 799.5,
    "perr": 0.6,
    "b": "exo"
  },
  {
    "n": "18 Del b",
    "p": 993.3,
    "perr": 3.2,
    "b": "exo"
  },
  {
    "n": "1SWASP J1407 b",
    "p": 3725,
    "perr": 900,
    "b": "exo"
  },
  {
    "n": "24 Sex b",
    "p": 452.8,
    "perr": 2.1,
    "b": "exo"
  },
  {
    "n": "24 Sex c",
    "p": 883,
    "perr": 32,
    "b": "exo"
  },
  {
    "n": "2M 0746+20 b",
    "p": 4640,
    "perr": 25,
    "b": "exo"
  },
  {
    "n": "2M 1938+46 b",
    "p": 416,
    "perr": 2,
    "b": "exo"
  },
  {
    "n": "2M 2140+16 b",
    "p": 7340,
    "perr": 584,
    "b": "exo"
  },
  {
    "n": "2M 2206-20 b",
    "p": 8686,
    "perr": 69.4,
    "b": "exo"
  },
  {
    "n": "30 Ari B b",
    "p": 335.1,
    "perr": 2.5,
    "b": "exo"
  },
  {
    "n": "38 Vir b",
    "p": 825.9,
    "perr": 6.2,
    "b": "exo"
  },
  {
    "n": "4 Uma b",
    "p": 269.3,
    "perr": 1.96,
    "b": "exo"
  },
  {
    "n": "42 Dra b",
    "p": 479.1,
    "perr": 6.2,
    "b": "exo"
  },
  {
    "n": "47 Uma b",
    "p": 1078,
    "perr": 2,
    "b": "exo"
  },
  {
    "n": "47 Uma c",
    "p": 2391,
    "perr": 100,
    "b": "exo"
  },
  {
    "n": "47 Uma d",
    "p": 14002,
    "perr": 4018,
    "b": "exo"
  },
  {
    "n": "51 Eri b",
    "p": 14965,
    "perr": 12775,
    "b": "exo"
  },
  {
    "n": "55 Cnc d",
    "p": 4867,
    "perr": 25,
    "b": "exo"
  },
  {
    "n": "55 Cnc f",
    "p": 260.91,
    "perr": 0.36,
    "b": "exo"
  },
  {
    "n": "6 Lyn b",
    "p": 899,
    "perr": 19,
    "b": "exo"
  },
  {
    "n": "61 Vir d",
    "p": 123.01,
    "perr": 0.55,
    "b": "exo"
  },
  {
    "n": "7 CMa b",
    "p": 796,
    "perr": 7.4,
    "b": "exo"
  },
  {
    "n": "70 Vir b",
    "p": 116.67,
    "perr": 0.01,
    "b": "exo"
  },
  {
    "n": "75 Cet b",
    "p": 691.9,
    "perr": 3.6,
    "b": "exo"
  },
  {
    "n": "8 Umi b",
    "p": 93.4,
    "perr": 4.5,
    "b": "exo"
  },
  {
    "n": "81 Cet b",
    "p": 952.7,
    "perr": 8.8,
    "b": "exo"
  },
  {
    "n": "91 Aqr b",
    "p": 181.4,
    "perr": 0.1,
    "b": "exo"
  },
  {
    "n": "Aldebaran b",
    "p": 628.96,
    "perr": 0.9,
    "b": "exo"
  },
  {
    "n": "BD+03 2562 b",
    "p": 481.9,
    "perr": 2.7,
    "b": "exo"
  },
  {
    "n": "BD+14 4559 b",
    "p": 268.94,
    "perr": 0.99,
    "b": "exo"
  },
  {
    "n": "BD+15 2375 b",
    "p": 153.22,
    "perr": 0.44,
    "b": "exo"
  },
  {
    "n": "BD+15 2940 b",
    "p": 137.48,
    "perr": 0.34,
    "b": "exo"
  },
  {
    "n": "BD+20 2457 b",
    "p": 379.63,
    "perr": 2.01,
    "b": "exo"
  },
  {
    "n": "BD+20 2457 c",
    "p": 621.99,
    "perr": 10.2,
    "b": "exo"
  },
  {
    "n": "BD+20 274 c",
    "p": 578.2,
    "perr": 3.4,
    "b": "exo"
  },
  {
    "n": "BD+24 4697 b",
    "p": 145.081,
    "perr": 0.016,
    "b": "exo"
  },
  {
    "n": "BD+26 1888 b",
    "p": 536.78,
    "perr": 0.25,
    "b": "exo"
  },
  {
    "n": "BD+48 738 b",
    "p": 392.6,
    "perr": 5.5,
    "b": "exo"
  },
  {
    "n": "BD+49 828 b",
    "p": 2590,
    "perr": 300,
    "b": "exo"
  },
  {
    "n": "BD-06 1339 c",
    "p": 125.94,
    "perr": 0.44,
    "b": "exo"
  },
  {
    "n": "BD-06 1339 d",
    "p": 500,
    "perr": 32,
    "b": "exo"
  },
  {
    "n": "BD-08 2823 c",
    "p": 237.6,
    "perr": 1.5,
    "b": "exo"
  },
  {
    "n": "BD-11 4672 b",
    "p": 1667,
    "perr": 33,
    "b": "exo"
  },
  {
    "n": "BD-17 63 b",
    "p": 655.6,
    "perr": 0.6,
    "b": "exo"
  },
  {
    "n": "CFBDS 1458 b",
    "p": 14227,
    "perr": 8600,
    "b": "exo"
  },
  {
    "n": "CoRoT-9 b",
    "p": 95.273804,
    "perr": 0.0014,
    "b": "exo"
  },
  {
    "n": "DE0823-49 b",
    "p": 247.75,
    "perr": 0.64,
    "b": "exo"
  },
  {
    "n": "DP Leo b",
    "p": 10230,
    "perr": 730,
    "b": "exo"
  },
  {
    "n": "FL Lyr b",
    "p": 4400,
    "perr": 180,
    "b": "exo"
  },
  {
    "n": "GJ 163 d",
    "p": 600.895,
    "perr": 7.56,
    "b": "exo"
  },
  {
    "n": "GJ 179 b",
    "p": 2288,
    "perr": 59,
    "b": "exo"
  },
  {
    "n": "GJ 229 A b",
    "p": 471,
    "perr": 22,
    "b": "exo"
  },
  {
    "n": "GJ 3021 b",
    "p": 133.71,
    "perr": 0.2,
    "b": "exo"
  },
  {
    "n": "GJ 3138 d",
    "p": 257.8,
    "perr": 3.6,
    "b": "exo"
  },
  {
    "n": "GJ 317 b",
    "p": 692,
    "perr": 2,
    "b": "exo"
  },
  {
    "n": "GJ 317 c",
    "p": 7300,
    "perr": 1.7976931348623157e+308,
    "b": "exo"
  },
  {
    "n": "GJ 328 b",
    "p": 4100,
    "perr": 300,
    "b": "exo"
  },
  {
    "n": "GJ 3293 c",
    "p": 122.6196,
    "perr": 0.24,
    "b": "exo"
  },
  {
    "n": "GJ 433 c",
    "p": 3693,
    "perr": 253,
    "b": "exo"
  },
  {
    "n": "GJ 649 b",
    "p": 598.3,
    "perr": 4.2,
    "b": "exo"
  },
  {
    "n": "GJ 667 C d",
    "p": 91.61,
    "perr": 0.81,
    "b": "exo"
  },
  {
    "n": "GJ 667 C e",
    "p": 62.24,
    "perr": 0.55,
    "b": "exo"
  },
  {
    "n": "GJ 667 C g",
    "p": 256.2,
    "perr": 13.8,
    "b": "exo"
  },
  {
    "n": "GJ 676 A b",
    "p": 1052.1,
    "perr": 0.4,
    "b": "exo"
  },
  {
    "n": "GJ 676 A c",
    "p": 7337,
    "perr": 95,
    "b": "exo"
  },
  {
    "n": "GJ 758 b",
    "p": 109000,
    "perr": 198000,
    "b": "exo"
  },
  {
    "n": "GJ 785 b",
    "p": 74.72,
    "perr": 0.1,
    "b": "exo"
  },
  {
    "n": "GJ 785 c",
    "p": 525.8,
    "perr": 9.2,
    "b": "exo"
  },
  {
    "n": "GJ 832 b",
    "p": 3416,
    "perr": 131,
    "b": "exo"
  },
  {
    "n": "GJ 849 b",
    "p": 1914,
    "perr": 26,
    "b": "exo"
  },
  {
    "n": "GJ 849 c",
    "p": 7049,
    "perr": 2155,
    "b": "exo"
  },
  {
    "n": "GJ 876 b",
    "p": 61.03,
    "perr": 3.81,
    "b": "exo"
  },
  {
    "n": "GJ 876 e",
    "p": 124.69,
    "perr": 90.04,
    "b": "exo"
  },
  {
    "n": "HAT-P-13 c",
    "p": 446.27,
    "perr": 0.22,
    "b": "exo"
  },
  {
    "n": "HAT-P-44 c",
    "p": 219.9,
    "perr": 4.5,
    "b": "exo"
  },
  {
    "n": "HAT-P-46 c",
    "p": 77.7,
    "perr": 0.6,
    "b": "exo"
  },
  {
    "n": "HD 100655 b",
    "p": 157.57,
    "perr": 0.65,
    "b": "exo"
  },
  {
    "n": "HD 100777 b",
    "p": 383.7,
    "perr": 1.2,
    "b": "exo"
  },
  {
    "n": "HD 10180 f",
    "p": 122.76,
    "perr": 0.17,
    "b": "exo"
  },
  {
    "n": "HD 10180 g",
    "p": 601.2,
    "perr": 8.1,
    "b": "exo"
  },
  {
    "n": "HD 10180 h",
    "p": 2222,
    "perr": 91,
    "b": "exo"
  },
  {
    "n": "HD 101930 b",
    "p": 70.46,
    "perr": 0.18,
    "b": "exo"
  },
  {
    "n": "HD 102272 b",
    "p": 127.58,
    "perr": 0.3,
    "b": "exo"
  },
  {
    "n": "HD 102272 c",
    "p": 520,
    "perr": 26,
    "b": "exo"
  },
  {
    "n": "HD 102329 b",
    "p": 778.1,
    "perr": 7.1,
    "b": "exo"
  },
  {
    "n": "HD 102365 b",
    "p": 122.1,
    "perr": 0.3,
    "b": "exo"
  },
  {
    "n": "HD 10442 b",
    "p": 1043,
    "perr": 9,
    "b": "exo"
  },
  {
    "n": "HD 104985 b",
    "p": 199.505,
    "perr": 0.085,
    "b": "exo"
  },
  {
    "n": "HD 106252 b",
    "p": 1600,
    "perr": 18,
    "b": "exo"
  },
  {
    "n": "HD 106270 b",
    "p": 2890,
    "perr": 390,
    "b": "exo"
  },
  {
    "n": "HD 10647 b",
    "p": 1003,
    "perr": 56,
    "b": "exo"
  },
  {
    "n": "HD 106515 A b",
    "p": 3630,
    "perr": 14.2,
    "b": "exo"
  },
  {
    "n": "HD 10697 b",
    "p": 1076.4,
    "perr": 2.4,
    "b": "exo"
  },
  {
    "n": "HD 108341 b",
    "p": 1129,
    "perr": 8,
    "b": "exo"
  },
  {
    "n": "HD 108863 b",
    "p": 443.4,
    "perr": 4.2,
    "b": "exo"
  },
  {
    "n": "HD 108874 b",
    "p": 395.4,
    "perr": 2.5,
    "b": "exo"
  },
  {
    "n": "HD 108874 c",
    "p": 1605.8,
    "perr": 88,
    "b": "exo"
  },
  {
    "n": "HD 109246 b",
    "p": 68.27,
    "perr": 0.13,
    "b": "exo"
  },
  {
    "n": "HD 110014 b",
    "p": 882.6,
    "perr": 21.5,
    "b": "exo"
  },
  {
    "n": "HD 110014 c",
    "p": 130,
    "perr": 0.9,
    "b": "exo"
  },
  {
    "n": "HD 111232 b",
    "p": 1143,
    "perr": 14,
    "b": "exo"
  },
  {
    "n": "HD 111591 b",
    "p": 1056.4,
    "perr": 14.3,
    "b": "exo"
  },
  {
    "n": "HD 113337 b",
    "p": 324,
    "perr": 3.3,
    "b": "exo"
  },
  {
    "n": "HD 113538 b",
    "p": 663.2,
    "perr": 7.4,
    "b": "exo"
  },
  {
    "n": "HD 113538 c",
    "p": 1818,
    "perr": 25,
    "b": "exo"
  },
  {
    "n": "HD 113996 b",
    "p": 610.2,
    "perr": 3.8,
    "b": "exo"
  },
  {
    "n": "HD 114386 b",
    "p": 937,
    "perr": 15.6,
    "b": "exo"
  },
  {
    "n": "HD 114613 b",
    "p": 3827,
    "perr": 105,
    "b": "exo"
  },
  {
    "n": "HD 114729 b",
    "p": 1135,
    "perr": 9,
    "b": "exo"
  },
  {
    "n": "HD 114762 b",
    "p": 83.9151,
    "perr": 0.003,
    "b": "exo"
  },
  {
    "n": "HD 114783 b",
    "p": 493.7,
    "perr": 1.8,
    "b": "exo"
  },
  {
    "n": "HD 11506 b",
    "p": 1270,
    "perr": 95,
    "b": "exo"
  },
  {
    "n": "HD 11506 c",
    "p": 170.46,
    "perr": 6,
    "b": "exo"
  },
  {
    "n": "HD 116029 b",
    "p": 670.2,
    "perr": 8.3,
    "b": "exo"
  },
  {
    "n": "HD 117207 b",
    "p": 2627.08,
    "perr": 63.51,
    "b": "exo"
  },
  {
    "n": "HD 11755 b",
    "p": 433.7,
    "perr": 3.2,
    "b": "exo"
  },
  {
    "n": "HD 117618 c",
    "p": 318,
    "perr": 2,
    "b": "exo"
  },
  {
    "n": "HD 119445 b",
    "p": 410.2,
    "perr": 0.6,
    "b": "exo"
  },
  {
    "n": "HD 11964 b",
    "p": 1945,
    "perr": 26,
    "b": "exo"
  },
  {
    "n": "HD 11977 b",
    "p": 711,
    "perr": 8,
    "b": "exo"
  },
  {
    "n": "HD 120084 b",
    "p": 2082,
    "perr": 24,
    "b": "exo"
  },
  {
    "n": "HD 121504 b",
    "p": 63.33,
    "perr": 0.03,
    "b": "exo"
  },
  {
    "n": "HD 122562 b",
    "p": 2777,
    "perr": 104,
    "b": "exo"
  },
  {
    "n": "HD 125612 b",
    "p": 502,
    "perr": 14,
    "b": "exo"
  },
  {
    "n": "HD 125612 d",
    "p": 3008,
    "perr": 202,
    "b": "exo"
  },
  {
    "n": "HD 12648 b",
    "p": 133.6,
    "perr": 0.5,
    "b": "exo"
  },
  {
    "n": "HD 126525 b",
    "p": 948.12,
    "perr": 21.966,
    "b": "exo"
  },
  {
    "n": "HD 12661 b",
    "p": 263.6,
    "perr": 1.2,
    "b": "exo"
  },
  {
    "n": "HD 12661 c",
    "p": 1708,
    "perr": 14,
    "b": "exo"
  },
  {
    "n": "HD 126614 b",
    "p": 1244,
    "perr": 17,
    "b": "exo"
  },
  {
    "n": "HD 128311 b",
    "p": 448.6,
    "perr": 6.8,
    "b": "exo"
  },
  {
    "n": "HD 128356 b",
    "p": 298.2,
    "perr": 1.6,
    "b": "exo"
  },
  {
    "n": "HD 129445 b",
    "p": 1840,
    "perr": 55,
    "b": "exo"
  },
  {
    "n": "HD 131496 b",
    "p": 883,
    "perr": 29,
    "b": "exo"
  },
  {
    "n": "HD 13189 b",
    "p": 471.6,
    "perr": 6,
    "b": "exo"
  },
  {
    "n": "HD 132406 b",
    "p": 974,
    "perr": 39,
    "b": "exo"
  },
  {
    "n": "HD 132563 B b",
    "p": 1544,
    "perr": 34,
    "b": "exo"
  },
  {
    "n": "HD 133131 A b",
    "p": 649,
    "perr": 3,
    "b": "exo"
  },
  {
    "n": "HD 133131 A c",
    "p": 3407,
    "perr": 970,
    "b": "exo"
  },
  {
    "n": "HD 133131 B b",
    "p": 6119,
    "perr": 831,
    "b": "exo"
  },
  {
    "n": "HD 134060 c",
    "p": 1160.9,
    "perr": 27.046,
    "b": "exo"
  },
  {
    "n": "HD 134113 b",
    "p": 201.68,
    "perr": 0.004,
    "b": "exo"
  },
  {
    "n": "HD 134606 d",
    "p": 459.26,
    "perr": 8.3238,
    "b": "exo"
  },
  {
    "n": "HD 134987 b",
    "p": 258.19,
    "perr": 0.07,
    "b": "exo"
  },
  {
    "n": "HD 134987 c",
    "p": 5000,
    "perr": 400,
    "b": "exo"
  },
  {
    "n": "HD 136352 d",
    "p": 106.72,
    "perr": 1.0284,
    "b": "exo"
  },
  {
    "n": "HD 136418 b",
    "p": 464.3,
    "perr": 3.2,
    "b": "exo"
  },
  {
    "n": "HD 137388 b",
    "p": 330,
    "perr": 4,
    "b": "exo"
  },
  {
    "n": "HD 13908 c",
    "p": 931,
    "perr": 17,
    "b": "exo"
  },
  {
    "n": "HD 13931 b",
    "p": 4218,
    "perr": 388,
    "b": "exo"
  },
  {
    "n": "HD 139357 b",
    "p": 1125.7,
    "perr": 9,
    "b": "exo"
  },
  {
    "n": "HD 14067 b",
    "p": 1455,
    "perr": 13,
    "b": "exo"
  },
  {
    "n": "HD 141399 b",
    "p": 94.44,
    "perr": 0.05,
    "b": "exo"
  },
  {
    "n": "HD 141399 c",
    "p": 201.99,
    "perr": 0.08,
    "b": "exo"
  },
  {
    "n": "HD 141399 d",
    "p": 1069.8,
    "perr": 6.7,
    "b": "exo"
  },
  {
    "n": "HD 141399 e",
    "p": 5000,
    "perr": 560,
    "b": "exo"
  },
  {
    "n": "HD 141937 b",
    "p": 653.22,
    "perr": 1.21,
    "b": "exo"
  },
  {
    "n": "HD 142 b",
    "p": 349.7,
    "perr": 1.2,
    "b": "exo"
  },
  {
    "n": "HD 142 c",
    "p": 6005,
    "perr": 477,
    "b": "exo"
  },
  {
    "n": "HD 142022 A b",
    "p": 1928,
    "perr": 53,
    "b": "exo"
  },
  {
    "n": "HD 142245 b",
    "p": 1299,
    "perr": 48,
    "b": "exo"
  },
  {
    "n": "HD 142415 b",
    "p": 386.3,
    "perr": 1.6,
    "b": "exo"
  },
  {
    "n": "HD 143361 b",
    "p": 1057,
    "perr": 20,
    "b": "exo"
  },
  {
    "n": "HD 143761 c",
    "p": 102.54,
    "perr": 0.17,
    "b": "exo"
  },
  {
    "n": "HD 145377 b",
    "p": 103.95,
    "perr": 0.13,
    "b": "exo"
  },
  {
    "n": "HD 145457 b",
    "p": 176.3,
    "perr": 0.39,
    "b": "exo"
  },
  {
    "n": "HD 145934 b",
    "p": 2730,
    "perr": 100,
    "b": "exo"
  },
  {
    "n": "HD 147018 c",
    "p": 1008,
    "perr": 18,
    "b": "exo"
  },
  {
    "n": "HD 147379 b",
    "p": 86.54,
    "perr": 0.07,
    "b": "exo"
  },
  {
    "n": "HD 147513 b",
    "p": 528.4,
    "perr": 6.3,
    "b": "exo"
  },
  {
    "n": "HD 147873 b",
    "p": 116.596,
    "perr": 0.023,
    "b": "exo"
  },
  {
    "n": "HD 147873 c",
    "p": 491.54,
    "perr": 0.79,
    "b": "exo"
  },
  {
    "n": "HD 148427 b",
    "p": 331.5,
    "perr": 3,
    "b": "exo"
  },
  {
    "n": "HD 1502 b",
    "p": 431.8,
    "perr": 3.1,
    "b": "exo"
  },
  {
    "n": "HD 150433 b",
    "p": 1096.2,
    "perr": 27.234,
    "b": "exo"
  },
  {
    "n": "HD 150706 b",
    "p": 5894,
    "perr": 5584,
    "b": "exo"
  },
  {
    "n": "HD 152079 b",
    "p": 2097,
    "perr": 930,
    "b": "exo"
  },
  {
    "n": "HD 152581 b",
    "p": 689,
    "perr": 13,
    "b": "exo"
  },
  {
    "n": "HD 153950 b",
    "p": 499.4,
    "perr": 3.6,
    "b": "exo"
  },
  {
    "n": "HD 154345 b",
    "p": 3538,
    "perr": 300,
    "b": "exo"
  },
  {
    "n": "HD 154672 b",
    "p": 163.91,
    "perr": 0.01,
    "b": "exo"
  },
  {
    "n": "HD 154857 b",
    "p": 408.6,
    "perr": 0.5,
    "b": "exo"
  },
  {
    "n": "HD 154857 c",
    "p": 3452,
    "perr": 105,
    "b": "exo"
  },
  {
    "n": "HD 155233 b",
    "p": 818.8,
    "perr": 12,
    "b": "exo"
  },
  {
    "n": "HD 155358 b",
    "p": 194.3,
    "perr": 0.3,
    "b": "exo"
  },
  {
    "n": "HD 155358 c",
    "p": 391.9,
    "perr": 1,
    "b": "exo"
  },
  {
    "n": "HD 156279 b",
    "p": 131.05,
    "perr": 0.54,
    "b": "exo"
  },
  {
    "n": "HD 156411 b",
    "p": 842.2,
    "perr": 14.5,
    "b": "exo"
  },
  {
    "n": "HD 158038 b",
    "p": 521,
    "perr": 6.9,
    "b": "exo"
  },
  {
    "n": "HD 159243 c",
    "p": 248.4,
    "perr": 4.9,
    "b": "exo"
  },
  {
    "n": "HD 159868 b",
    "p": 1178.4,
    "perr": 8.8,
    "b": "exo"
  },
  {
    "n": "HD 159868 c",
    "p": 352.3,
    "perr": 1.3,
    "b": "exo"
  },
  {
    "n": "HD 1605 b",
    "p": 577.9,
    "perr": 5.6,
    "b": "exo"
  },
  {
    "n": "HD 1605 c",
    "p": 2111,
    "perr": 42,
    "b": "exo"
  },
  {
    "n": "HD 160508 b",
    "p": 178.9049,
    "perr": 0.0074,
    "b": "exo"
  },
  {
    "n": "HD 16141 b",
    "p": 75.82,
    "perr": 0.4,
    "b": "exo"
  },
  {
    "n": "HD 16175 b",
    "p": 995.4,
    "perr": 2.8,
    "b": "exo"
  },
  {
    "n": "HD 162004 b",
    "p": 3117,
    "perr": 42,
    "b": "exo"
  },
  {
    "n": "HD 163607 b",
    "p": 75.229,
    "perr": 0.02,
    "b": "exo"
  },
  {
    "n": "HD 163607 c",
    "p": 1314,
    "perr": 8,
    "b": "exo"
  },
  {
    "n": "HD 164509 b",
    "p": 282.4,
    "perr": 3.8,
    "b": "exo"
  },
  {
    "n": "HD 164604 b",
    "p": 606.4,
    "perr": 9,
    "b": "exo"
  },
  {
    "n": "HD 164922 b",
    "p": 1201.1,
    "perr": 5.6,
    "b": "exo"
  },
  {
    "n": "HD 164922 c",
    "p": 75.765,
    "perr": 0.058,
    "b": "exo"
  },
  {
    "n": "HD 165155 b",
    "p": 434.5,
    "perr": 2.1,
    "b": "exo"
  },
  {
    "n": "HD 1666 b",
    "p": 270,
    "perr": 0.8,
    "b": "exo"
  },
  {
    "n": "HD 167042 b",
    "p": 416.1,
    "perr": 4,
    "b": "exo"
  },
  {
    "n": "HD 168443 c",
    "p": 1749.83,
    "perr": 0.57,
    "b": "exo"
  },
  {
    "n": "HD 1690 b",
    "p": 533,
    "perr": 1.7,
    "b": "exo"
  },
  {
    "n": "HD 169830 b",
    "p": 225.62,
    "perr": 0.22,
    "b": "exo"
  },
  {
    "n": "HD 169830 c",
    "p": 2102,
    "perr": 264,
    "b": "exo"
  },
  {
    "n": "HD 170469 b",
    "p": 1145,
    "perr": 18,
    "b": "exo"
  },
  {
    "n": "HD 17092 b",
    "p": 359.9,
    "perr": 2.4,
    "b": "exo"
  },
  {
    "n": "HD 171028 b",
    "p": 550,
    "perr": 3,
    "b": "exo"
  },
  {
    "n": "HD 171238 b",
    "p": 1523,
    "perr": 45,
    "b": "exo"
  },
  {
    "n": "HD 173416 b",
    "p": 323.6,
    "perr": 2.2,
    "b": "exo"
  },
  {
    "n": "HD 175167 b",
    "p": 1290,
    "perr": 22,
    "b": "exo"
  },
  {
    "n": "HD 175370 b",
    "p": 349.5,
    "perr": 4.5,
    "b": "exo"
  },
  {
    "n": "HD 175541 b",
    "p": 297.3,
    "perr": 6,
    "b": "exo"
  },
  {
    "n": "HD 176051 b",
    "p": 1016,
    "perr": 40,
    "b": "exo"
  },
  {
    "n": "HD 17674 b",
    "p": 623.8,
    "perr": 1.6,
    "b": "exo"
  },
  {
    "n": "HD 177830 b",
    "p": 406.6,
    "perr": 0.4,
    "b": "exo"
  },
  {
    "n": "HD 177830 c",
    "p": 110.9,
    "perr": 0.3,
    "b": "exo"
  },
  {
    "n": "HD 178911 B b",
    "p": 71.487,
    "perr": 0.018,
    "b": "exo"
  },
  {
    "n": "HD 180314 b",
    "p": 396.03,
    "perr": 0.62,
    "b": "exo"
  },
  {
    "n": "HD 180902 b",
    "p": 479,
    "perr": 13,
    "b": "exo"
  },
  {
    "n": "HD 181342 b",
    "p": 562,
    "perr": 6,
    "b": "exo"
  },
  {
    "n": "HD 181433 c",
    "p": 962,
    "perr": 15,
    "b": "exo"
  },
  {
    "n": "HD 181433 d",
    "p": 2172,
    "perr": 158,
    "b": "exo"
  },
  {
    "n": "HD 181720 b",
    "p": 956,
    "perr": 14,
    "b": "exo"
  },
  {
    "n": "HD 183263 b",
    "p": 626.5,
    "perr": 1.1,
    "b": "exo"
  },
  {
    "n": "HD 183263 c",
    "p": 2950,
    "perr": 340,
    "b": "exo"
  },
  {
    "n": "HD 187123 c",
    "p": 3810,
    "perr": 420,
    "b": "exo"
  },
  {
    "n": "HD 18742 b",
    "p": 772,
    "perr": 11,
    "b": "exo"
  },
  {
    "n": "HD 188015 b",
    "p": 456.46,
    "perr": 9.12,
    "b": "exo"
  },
  {
    "n": "HD 190228 b",
    "p": 1146,
    "perr": 16,
    "b": "exo"
  },
  {
    "n": "HD 190360 b",
    "p": 2867.9,
    "perr": 7.7,
    "b": "exo"
  },
  {
    "n": "HD 190647 b",
    "p": 1038.1,
    "perr": 4.9,
    "b": "exo"
  },
  {
    "n": "HD 191806 b",
    "p": 1606.3,
    "perr": 7.2,
    "b": "exo"
  },
  {
    "n": "HD 192699 b",
    "p": 351.5,
    "perr": 6,
    "b": "exo"
  },
  {
    "n": "HD 196067 b",
    "p": 3638,
    "perr": 185,
    "b": "exo"
  },
  {
    "n": "HD 196885 A b",
    "p": 1326,
    "perr": 3.7,
    "b": "exo"
  },
  {
    "n": "HD 197037 b",
    "p": 1035.7,
    "perr": 13,
    "b": "exo"
  },
  {
    "n": "HD 19994 b",
    "p": 535.7,
    "perr": 3.1,
    "b": "exo"
  },
  {
    "n": "HD 200964 b",
    "p": 613.8,
    "perr": 1.3,
    "b": "exo"
  },
  {
    "n": "HD 200964 c",
    "p": 825,
    "perr": 5.1,
    "b": "exo"
  },
  {
    "n": "HD 202206 B",
    "p": 256.33,
    "perr": 0.02,
    "b": "exo"
  },
  {
    "n": "HD 202206 c",
    "p": 1260,
    "perr": 11,
    "b": "exo"
  },
  {
    "n": "HD 20367 b",
    "p": 500,
    "perr": 6,
    "b": "exo"
  },
  {
    "n": "HD 2039 b",
    "p": 1120,
    "perr": 23,
    "b": "exo"
  },
  {
    "n": "HD 204313 b",
    "p": 2024.1,
    "perr": 3.1,
    "b": "exo"
  },
  {
    "n": "HD 204313 d",
    "p": 2831.6,
    "perr": 150,
    "b": "exo"
  },
  {
    "n": "HD 204941 b",
    "p": 1733,
    "perr": 74,
    "b": "exo"
  },
  {
    "n": "HD 205739 b",
    "p": 279.8,
    "perr": 0.1,
    "b": "exo"
  },
  {
    "n": "HD 206610 b",
    "p": 610,
    "perr": 13,
    "b": "exo"
  },
  {
    "n": "HD 20781 c",
    "p": 85.131,
    "perr": 0.1161,
    "b": "exo"
  },
  {
    "n": "HD 20782 b",
    "p": 591.9,
    "perr": 2.8,
    "b": "exo"
  },
  {
    "n": "HD 207832 b",
    "p": 161.97,
    "perr": 0.97,
    "b": "exo"
  },
  {
    "n": "HD 207832 c",
    "p": 1155.7,
    "perr": 71.9,
    "b": "exo"
  },
  {
    "n": "HD 20794 d",
    "p": 88.9,
    "perr": 0.37,
    "b": "exo"
  },
  {
    "n": "HD 20794 e",
    "p": 147.02,
    "perr": 1.43,
    "b": "exo"
  },
  {
    "n": "HD 208487 b",
    "p": 129.8,
    "perr": 0.4,
    "b": "exo"
  },
  {
    "n": "HD 208527 b",
    "p": 875.5,
    "perr": 5.8,
    "b": "exo"
  },
  {
    "n": "HD 20868 b",
    "p": 380.85,
    "perr": 0.09,
    "b": "exo"
  },
  {
    "n": "HD 208897 b",
    "p": 352.7,
    "perr": 1.7,
    "b": "exo"
  },
  {
    "n": "HD 210277 b",
    "p": 442.1,
    "perr": 0.4,
    "b": "exo"
  },
  {
    "n": "HD 210702 b",
    "p": 354.8,
    "perr": 1.1,
    "b": "exo"
  },
  {
    "n": "HD 211847 b",
    "p": 7930,
    "perr": 2500,
    "b": "exo"
  },
  {
    "n": "HD 212771 b",
    "p": 373.3,
    "perr": 3.4,
    "b": "exo"
  },
  {
    "n": "HD 213240 b",
    "p": 951,
    "perr": 42,
    "b": "exo"
  },
  {
    "n": "HD 214823 b",
    "p": 1877,
    "perr": 15,
    "b": "exo"
  },
  {
    "n": "HD 215497 c",
    "p": 567.94,
    "perr": 2.7,
    "b": "exo"
  },
  {
    "n": "HD 216435 b",
    "p": 1311,
    "perr": 49,
    "b": "exo"
  },
  {
    "n": "HD 216437 b",
    "p": 1256,
    "perr": 35,
    "b": "exo"
  },
  {
    "n": "HD 216536 b",
    "p": 148.6,
    "perr": 0.7,
    "b": "exo"
  },
  {
    "n": "HD 216770 b",
    "p": 118.45,
    "perr": 0.4,
    "b": "exo"
  },
  {
    "n": "HD 217107 c",
    "p": 4210,
    "perr": 190,
    "b": "exo"
  },
  {
    "n": "HD 217786 b",
    "p": 1319,
    "perr": 4,
    "b": "exo"
  },
  {
    "n": "HD 218566 b",
    "p": 225.7,
    "perr": 0.4,
    "b": "exo"
  },
  {
    "n": "HD 219077 b",
    "p": 5501,
    "perr": 130,
    "b": "exo"
  },
  {
    "n": "HD 219134 e",
    "p": 1190,
    "perr": 379,
    "b": "exo"
  },
  {
    "n": "HD 219134 g",
    "p": 94.2,
    "perr": 0.2,
    "b": "exo"
  },
  {
    "n": "HD 219134 h",
    "p": 2198,
    "perr": 51,
    "b": "exo"
  },
  {
    "n": "HD 219415 b",
    "p": 2093.3,
    "perr": 32.7,
    "b": "exo"
  },
  {
    "n": "HD 219828 c",
    "p": 4791,
    "perr": 75,
    "b": "exo"
  },
  {
    "n": "HD 220074 b",
    "p": 672.1,
    "perr": 3.7,
    "b": "exo"
  },
  {
    "n": "HD 220689 b",
    "p": 2209,
    "perr": 81,
    "b": "exo"
  },
  {
    "n": "HD 220773 b",
    "p": 3724.7,
    "perr": 463,
    "b": "exo"
  },
  {
    "n": "HD 220842 b",
    "p": 218.47,
    "perr": 0.19,
    "b": "exo"
  },
  {
    "n": "HD 221287 b",
    "p": 456.1,
    "perr": 7.7,
    "b": "exo"
  },
  {
    "n": "HD 221585 b",
    "p": 1173,
    "perr": 16,
    "b": "exo"
  },
  {
    "n": "HD 222076 b",
    "p": 871,
    "perr": 19,
    "b": "exo"
  },
  {
    "n": "HD 222155 b",
    "p": 3999,
    "perr": 541,
    "b": "exo"
  },
  {
    "n": "HD 222582 b",
    "p": 572.38,
    "perr": 0.61,
    "b": "exo"
  },
  {
    "n": "HD 224538 b",
    "p": 1189.1,
    "perr": 5.1,
    "b": "exo"
  },
  {
    "n": "HD 22781 b",
    "p": 528.07,
    "perr": 0.14,
    "b": "exo"
  },
  {
    "n": "HD 23079 b",
    "p": 730.6,
    "perr": 5.7,
    "b": "exo"
  },
  {
    "n": "HD 23127 b",
    "p": 1214,
    "perr": 9,
    "b": "exo"
  },
  {
    "n": "HD 231701 b",
    "p": 141.89,
    "perr": 0.15,
    "b": "exo"
  },
  {
    "n": "HD 233604 b",
    "p": 192,
    "perr": 0.22,
    "b": "exo"
  },
  {
    "n": "HD 23596 b",
    "p": 1565,
    "perr": 21,
    "b": "exo"
  },
  {
    "n": "HD 240210 b",
    "p": 501.75,
    "perr": 2.33,
    "b": "exo"
  },
  {
    "n": "HD 240237 b",
    "p": 745.7,
    "perr": 13.8,
    "b": "exo"
  },
  {
    "n": "HD 24040 b",
    "p": 3668,
    "perr": 170,
    "b": "exo"
  },
  {
    "n": "HD 24064 b",
    "p": 555.6,
    "perr": 3,
    "b": "exo"
  },
  {
    "n": "HD 25171 b",
    "p": 1845,
    "perr": 15,
    "b": "exo"
  },
  {
    "n": "HD 27442 b",
    "p": 415.2,
    "perr": 0.5,
    "b": "exo"
  },
  {
    "n": "HD 27631 b",
    "p": 2208,
    "perr": 66,
    "b": "exo"
  },
  {
    "n": "HD 27894 d",
    "p": 5174,
    "perr": 171,
    "b": "exo"
  },
  {
    "n": "HD 28185 b",
    "p": 383,
    "perr": 2,
    "b": "exo"
  },
  {
    "n": "HD 28254 b",
    "p": 1116,
    "perr": 26,
    "b": "exo"
  },
  {
    "n": "HD 283668 b",
    "p": 2558,
    "perr": 8,
    "b": "exo"
  },
  {
    "n": "HD 28678 b",
    "p": 387.1,
    "perr": 4.2,
    "b": "exo"
  },
  {
    "n": "HD 29021 b",
    "p": 1362.3,
    "perr": 4.6,
    "b": "exo"
  },
  {
    "n": "HD 290327 b",
    "p": 2443,
    "perr": 117,
    "b": "exo"
  },
  {
    "n": "HD 2952 b",
    "p": 311.6,
    "perr": 1.7,
    "b": "exo"
  },
  {
    "n": "HD 30177 b",
    "p": 2532.5,
    "perr": 10.6,
    "b": "exo"
  },
  {
    "n": "HD 30177 c",
    "p": 6921,
    "perr": 621,
    "b": "exo"
  },
  {
    "n": "HD 30562 b",
    "p": 1157,
    "perr": 27,
    "b": "exo"
  },
  {
    "n": "HD 30669 b",
    "p": 1684,
    "perr": 61,
    "b": "exo"
  },
  {
    "n": "HD 30856 b",
    "p": 912,
    "perr": 41,
    "b": "exo"
  },
  {
    "n": "HD 31253 b",
    "p": 466,
    "perr": 3,
    "b": "exo"
  },
  {
    "n": "HD 31527 d",
    "p": 274.49,
    "perr": 7.8133,
    "b": "exo"
  },
  {
    "n": "HD 32518 b",
    "p": 157.54,
    "perr": 0.38,
    "b": "exo"
  },
  {
    "n": "HD 32963 b",
    "p": 2372,
    "perr": 26,
    "b": "exo"
  },
  {
    "n": "HD 33142 b",
    "p": 326.6,
    "perr": 3.9,
    "b": "exo"
  },
  {
    "n": "HD 33564 b",
    "p": 388,
    "perr": 3,
    "b": "exo"
  },
  {
    "n": "HD 33844 b",
    "p": 551.4,
    "perr": 7.8,
    "b": "exo"
  },
  {
    "n": "HD 33844 c",
    "p": 916,
    "perr": 29.5,
    "b": "exo"
  },
  {
    "n": "HD 34445 b",
    "p": 1056.7,
    "perr": 4.7,
    "b": "exo"
  },
  {
    "n": "HD 34445 c",
    "p": 214.67,
    "perr": 0.45,
    "b": "exo"
  },
  {
    "n": "HD 34445 d",
    "p": 117.87,
    "perr": 0.18,
    "b": "exo"
  },
  {
    "n": "HD 34445 f",
    "p": 676.8,
    "perr": 7.9,
    "b": "exo"
  },
  {
    "n": "HD 34445 g",
    "p": 5700,
    "perr": 1500,
    "b": "exo"
  },
  {
    "n": "HD 35759 b",
    "p": 82.467,
    "perr": 0.019,
    "b": "exo"
  },
  {
    "n": "HD 3651 b",
    "p": 62.218,
    "perr": 0.015,
    "b": "exo"
  },
  {
    "n": "HD 37124 b",
    "p": 154.378,
    "perr": 0.028,
    "b": "exo"
  },
  {
    "n": "HD 37124 c",
    "p": 885.5,
    "perr": 5.1,
    "b": "exo"
  },
  {
    "n": "HD 37124 d",
    "p": 1862,
    "perr": 38,
    "b": "exo"
  },
  {
    "n": "HD 37605 c",
    "p": 2720,
    "perr": 57,
    "b": "exo"
  },
  {
    "n": "HD 38283 b",
    "p": 363.2,
    "perr": 1.6,
    "b": "exo"
  },
  {
    "n": "HD 38529 c",
    "p": 2134.76,
    "perr": 0.4,
    "b": "exo"
  },
  {
    "n": "HD 38801 b",
    "p": 696.3,
    "perr": 2.7,
    "b": "exo"
  },
  {
    "n": "HD 38858 b",
    "p": 407.15,
    "perr": 4.2857,
    "b": "exo"
  },
  {
    "n": "HD 39091 b",
    "p": 2049,
    "perr": 150,
    "b": "exo"
  },
  {
    "n": "HD 39392 b",
    "p": 394.3,
    "perr": 1.4,
    "b": "exo"
  },
  {
    "n": "HD 40307 g",
    "p": 197.8,
    "perr": 9,
    "b": "exo"
  },
  {
    "n": "HD 40956 b",
    "p": 578.6,
    "perr": 3.3,
    "b": "exo"
  },
  {
    "n": "HD 40979 b",
    "p": 264.1,
    "perr": 0.23,
    "b": "exo"
  },
  {
    "n": "HD 41004 A b",
    "p": 963,
    "perr": 38,
    "b": "exo"
  },
  {
    "n": "HD 4113 b",
    "p": 526.62,
    "perr": 0.3,
    "b": "exo"
  },
  {
    "n": "HD 42012 b",
    "p": 857.5,
    "perr": 6.2,
    "b": "exo"
  },
  {
    "n": "HD 4203 b",
    "p": 437.05,
    "perr": 0.27,
    "b": "exo"
  },
  {
    "n": "HD 4203 c",
    "p": 6700,
    "perr": 4500,
    "b": "exo"
  },
  {
    "n": "HD 4208 b",
    "p": 828,
    "perr": 8.1,
    "b": "exo"
  },
  {
    "n": "HD 42618 b",
    "p": 149.61,
    "perr": 0.37,
    "b": "exo"
  },
  {
    "n": "HD 4313 b",
    "p": 356,
    "perr": 2.6,
    "b": "exo"
  },
  {
    "n": "HD 43197 b",
    "p": 327.8,
    "perr": 1.2,
    "b": "exo"
  },
  {
    "n": "HD 44219 b",
    "p": 472.3,
    "perr": 5,
    "b": "exo"
  },
  {
    "n": "HD 45350 b",
    "p": 890.76,
    "perr": 37.42,
    "b": "exo"
  },
  {
    "n": "HD 45364 b",
    "p": 226.93,
    "perr": 0.37,
    "b": "exo"
  },
  {
    "n": "HD 45364 c",
    "p": 342.85,
    "perr": 0.28,
    "b": "exo"
  },
  {
    "n": "HD 47186 c",
    "p": 1353.6,
    "perr": 57.1,
    "b": "exo"
  },
  {
    "n": "HD 4732 b",
    "p": 360.2,
    "perr": 1.4,
    "b": "exo"
  },
  {
    "n": "HD 4732 c",
    "p": 2732,
    "perr": 81,
    "b": "exo"
  },
  {
    "n": "HD 47366 b",
    "p": 363.3,
    "perr": 2.5,
    "b": "exo"
  },
  {
    "n": "HD 47366 c",
    "p": 684.7,
    "perr": 5,
    "b": "exo"
  },
  {
    "n": "HD 4747 b",
    "p": 13835.67,
    "perr": 314,
    "b": "exo"
  },
  {
    "n": "HD 48265 b",
    "p": 700,
    "perr": 8,
    "b": "exo"
  },
  {
    "n": "HD 50499 b",
    "p": 2482.7,
    "perr": 110,
    "b": "exo"
  },
  {
    "n": "HD 50554 b",
    "p": 1293,
    "perr": 37,
    "b": "exo"
  },
  {
    "n": "HD 51608 c",
    "p": 95.415,
    "perr": 0.3908,
    "b": "exo"
  },
  {
    "n": "HD 52265 b",
    "p": 119.6,
    "perr": 0.4,
    "b": "exo"
  },
  {
    "n": "HD 5319 b",
    "p": 675,
    "perr": 17,
    "b": "exo"
  },
  {
    "n": "HD 5319 c",
    "p": 886,
    "perr": 8,
    "b": "exo"
  },
  {
    "n": "HD 5583 b",
    "p": 139.35,
    "perr": 0.22,
    "b": "exo"
  },
  {
    "n": "HD 5608 b",
    "p": 792.6,
    "perr": 7.7,
    "b": "exo"
  },
  {
    "n": "HD 564 b",
    "p": 492.3,
    "perr": 2.3,
    "b": "exo"
  },
  {
    "n": "HD 5891 b",
    "p": 177.11,
    "perr": 0.31,
    "b": "exo"
  },
  {
    "n": "HD 59686 A b",
    "p": 299.36,
    "perr": 0.26,
    "b": "exo"
  },
  {
    "n": "HD 60532 b",
    "p": 201.83,
    "perr": 0.14,
    "b": "exo"
  },
  {
    "n": "HD 60532 c",
    "p": 607.06,
    "perr": 2.1,
    "b": "exo"
  },
  {
    "n": "HD 62509 b",
    "p": 589.64,
    "perr": 0.81,
    "b": "exo"
  },
  {
    "n": "HD 63765 b",
    "p": 358,
    "perr": 1,
    "b": "exo"
  },
  {
    "n": "HD 65216 b",
    "p": 572.4,
    "perr": 0.21,
    "b": "exo"
  },
  {
    "n": "HD 65216 c",
    "p": 152.6,
    "perr": 0.6,
    "b": "exo"
  },
  {
    "n": "HD 66141 b",
    "p": 480.5,
    "perr": 0.5,
    "b": "exo"
  },
  {
    "n": "HD 66428 b",
    "p": 1973,
    "perr": 31,
    "b": "exo"
  },
  {
    "n": "HD 67087 b",
    "p": 352.2,
    "perr": 1.7,
    "b": "exo"
  },
  {
    "n": "HD 67087 c",
    "p": 2374,
    "perr": 193,
    "b": "exo"
  },
  {
    "n": "HD 6718 b",
    "p": 2496,
    "perr": 176,
    "b": "exo"
  },
  {
    "n": "HD 68402 b",
    "p": 1103,
    "perr": 33,
    "b": "exo"
  },
  {
    "n": "HD 69830 d",
    "p": 197,
    "perr": 3,
    "b": "exo"
  },
  {
    "n": "HD 70642 b",
    "p": 2231,
    "perr": 400,
    "b": "exo"
  },
  {
    "n": "HD 7199 b",
    "p": 615,
    "perr": 7,
    "b": "exo"
  },
  {
    "n": "HD 72659 b",
    "p": 3658,
    "perr": 32,
    "b": "exo"
  },
  {
    "n": "HD 73267 b",
    "p": 1260,
    "perr": 7,
    "b": "exo"
  },
  {
    "n": "HD 73526 b",
    "p": 188.9,
    "perr": 0.1,
    "b": "exo"
  },
  {
    "n": "HD 73526 c",
    "p": 379.1,
    "perr": 0.5,
    "b": "exo"
  },
  {
    "n": "HD 73534 b",
    "p": 1800,
    "perr": 110,
    "b": "exo"
  },
  {
    "n": "HD 74156 c",
    "p": 2448.9,
    "perr": 5.5,
    "b": "exo"
  },
  {
    "n": "HD 7449 b",
    "p": 1275,
    "perr": 15,
    "b": "exo"
  },
  {
    "n": "HD 7449 c",
    "p": 4046,
    "perr": 186,
    "b": "exo"
  },
  {
    "n": "HD 75784 b",
    "p": 341.7,
    "perr": 6.1,
    "b": "exo"
  },
  {
    "n": "HD 75784 c",
    "p": 5040,
    "perr": 3414,
    "b": "exo"
  },
  {
    "n": "HD 75898 b",
    "p": 418.2,
    "perr": 5.7,
    "b": "exo"
  },
  {
    "n": "HD 76920 b",
    "p": 415.4,
    "perr": 0.2,
    "b": "exo"
  },
  {
    "n": "HD 77065 b",
    "p": 119.1135,
    "perr": 0.0027,
    "b": "exo"
  },
  {
    "n": "HD 79498 b",
    "p": 1966,
    "perr": 41,
    "b": "exo"
  },
  {
    "n": "HD 80606 b",
    "p": 111.43637,
    "perr": 0.0009,
    "b": "exo"
  },
  {
    "n": "HD 81040 b",
    "p": 1001.7,
    "perr": 7,
    "b": "exo"
  },
  {
    "n": "HD 81688 b",
    "p": 184.02,
    "perr": 0.18,
    "b": "exo"
  },
  {
    "n": "HD 82886 b",
    "p": 705,
    "perr": 34,
    "b": "exo"
  },
  {
    "n": "HD 82943 d",
    "p": 1078,
    "perr": 13,
    "b": "exo"
  },
  {
    "n": "HD 8535 b",
    "p": 1313,
    "perr": 28,
    "b": "exo"
  },
  {
    "n": "HD 85390 b",
    "p": 788,
    "perr": 25,
    "b": "exo"
  },
  {
    "n": "HD 85390 c",
    "p": 3700,
    "perr": 840,
    "b": "exo"
  },
  {
    "n": "HD 8574 b",
    "p": 227.55,
    "perr": 0.77,
    "b": "exo"
  },
  {
    "n": "HD 86226 b",
    "p": 1534,
    "perr": 280,
    "b": "exo"
  },
  {
    "n": "HD 86264 b",
    "p": 1475,
    "perr": 55,
    "b": "exo"
  },
  {
    "n": "HD 8673 b",
    "p": 1634,
    "perr": 17,
    "b": "exo"
  },
  {
    "n": "HD 86950 b",
    "p": 1270,
    "perr": 57,
    "b": "exo"
  },
  {
    "n": "HD 87646 A c",
    "p": 674,
    "perr": 4,
    "b": "exo"
  },
  {
    "n": "HD 87883 b",
    "p": 2754,
    "perr": 87,
    "b": "exo"
  },
  {
    "n": "HD 89307 b",
    "p": 2199,
    "perr": 61,
    "b": "exo"
  },
  {
    "n": "HD 89744 b",
    "p": 256,
    "perr": 0.7,
    "b": "exo"
  },
  {
    "n": "HD 89744 c",
    "p": 85.2,
    "perr": 0.1,
    "b": "exo"
  },
  {
    "n": "HD 9174 b",
    "p": 1179,
    "perr": 34,
    "b": "exo"
  },
  {
    "n": "HD 92788 b",
    "p": 325.81,
    "perr": 0.26,
    "b": "exo"
  },
  {
    "n": "HD 92788 c",
    "p": 162,
    "perr": 3,
    "b": "exo"
  },
  {
    "n": "HD 93083 b",
    "p": 143.58,
    "perr": 0.6,
    "b": "exo"
  },
  {
    "n": "HD 9446 c",
    "p": 192.9,
    "perr": 0.9,
    "b": "exo"
  },
  {
    "n": "HD 95089 b",
    "p": 507,
    "perr": 16,
    "b": "exo"
  },
  {
    "n": "HD 95127 b",
    "p": 482,
    "perr": 5,
    "b": "exo"
  },
  {
    "n": "HD 95872 b",
    "p": 4375,
    "perr": 169,
    "b": "exo"
  },
  {
    "n": "HD 96063 b",
    "p": 361.1,
    "perr": 9.9,
    "b": "exo"
  },
  {
    "n": "HD 96127 b",
    "p": 647.3,
    "perr": 16.8,
    "b": "exo"
  },
  {
    "n": "HD 96167 b",
    "p": 498.9,
    "perr": 1,
    "b": "exo"
  },
  {
    "n": "HD 96700 c",
    "p": 103.49,
    "perr": 0.5794,
    "b": "exo"
  },
  {
    "n": "HD 98219 b",
    "p": 436.9,
    "perr": 4.5,
    "b": "exo"
  },
  {
    "n": "HD 98649 b",
    "p": 4951,
    "perr": 465,
    "b": "exo"
  },
  {
    "n": "HD 99109 b",
    "p": 439.3,
    "perr": 5.6,
    "b": "exo"
  },
  {
    "n": "HD 99706 b",
    "p": 868,
    "perr": 31,
    "b": "exo"
  },
  {
    "n": "HIP 105854 b",
    "p": 184.2,
    "perr": 0.5,
    "b": "exo"
  },
  {
    "n": "HIP 107773 b",
    "p": 144.3,
    "perr": 0.5,
    "b": "exo"
  },
  {
    "n": "HIP 109384 b",
    "p": 499.48,
    "perr": 0.32,
    "b": "exo"
  },
  {
    "n": "HIP 109600 b",
    "p": 232.08,
    "perr": 0.15,
    "b": "exo"
  },
  {
    "n": "HIP 11915",
    "p": 3830,
    "perr": 150,
    "b": "exo"
  },
  {
    "n": "HIP 14810 c",
    "p": 147.73,
    "perr": 0.065,
    "b": "exo"
  },
  {
    "n": "HIP 14810 d",
    "p": 962,
    "perr": 15,
    "b": "exo"
  },
  {
    "n": "HIP 41378 d",
    "p": 157,
    "perr": 163,
    "b": "exo"
  },
  {
    "n": "HIP 41378 e",
    "p": 131,
    "perr": 61,
    "b": "exo"
  },
  {
    "n": "HIP 41378 f",
    "p": 324,
    "perr": 121,
    "b": "exo"
  },
  {
    "n": "HIP 5158 b",
    "p": 345.63,
    "perr": 1.99,
    "b": "exo"
  },
  {
    "n": "HIP 5158 c",
    "p": 9018,
    "perr": 3181,
    "b": "exo"
  },
  {
    "n": "HIP 57274 d",
    "p": 431.7,
    "perr": 8.5,
    "b": "exo"
  },
  {
    "n": "HIP 65407 c",
    "p": 67.3,
    "perr": 0.08,
    "b": "exo"
  },
  {
    "n": "HIP 65891 b",
    "p": 1084.5,
    "perr": 23.2,
    "b": "exo"
  },
  {
    "n": "HIP 67537 b",
    "p": 2592.5,
    "perr": 116.1,
    "b": "exo"
  },
  {
    "n": "HIP 67851 b",
    "p": 88.9,
    "perr": 0.1,
    "b": "exo"
  },
  {
    "n": "HIP 67851 c",
    "p": 2131.8,
    "perr": 88.3,
    "b": "exo"
  },
  {
    "n": "HIP 70849 b",
    "p": 10000,
    "perr": 8000,
    "b": "exo"
  },
  {
    "n": "HIP 74890 b",
    "p": 822.3,
    "perr": 16.8,
    "b": "exo"
  },
  {
    "n": "HIP 75458 b",
    "p": 510.72,
    "perr": 0.07,
    "b": "exo"
  },
  {
    "n": "HIP 79431 b",
    "p": 111.7,
    "perr": 0.7,
    "b": "exo"
  },
  {
    "n": "HIP 8541 b",
    "p": 1560,
    "perr": 54,
    "b": "exo"
  },
  {
    "n": "HIP 97233 b",
    "p": 1058.8,
    "perr": 6.7,
    "b": "exo"
  },
  {
    "n": "HR 810 b",
    "p": 320.1,
    "perr": 2.1,
    "b": "exo"
  },
  {
    "n": "HU Aqr (AB) c",
    "p": 5646,
    "perr": 8,
    "b": "exo"
  },
  {
    "n": "HW Vir (AB) b",
    "p": 4640,
    "perr": 73,
    "b": "exo"
  },
  {
    "n": "KELT-6 c",
    "p": 1276,
    "perr": 81,
    "b": "exo"
  },
  {
    "n": "KIC 10024862 b",
    "p": 567.0445,
    "perr": 0.02557,
    "b": "exo"
  },
  {
    "n": "KIC 10255705 b",
    "p": 707.3793,
    "perr": 0.0039,
    "b": "exo"
  },
  {
    "n": "KIC 11152511 b",
    "p": 287.363,
    "perr": 0.0433,
    "b": "exo"
  },
  {
    "n": "KIC 12454613 b",
    "p": 736.3819,
    "perr": 0.0065,
    "b": "exo"
  },
  {
    "n": "KIC 5010054 b",
    "p": 904.24,
    "perr": 0.0146,
    "b": "exo"
  },
  {
    "n": "KIC 5094412 b",
    "p": 276.88,
    "perr": 0.0258,
    "b": "exo"
  },
  {
    "n": "KIC 5095269(AB) b",
    "p": 237.70817,
    "perr": 0.08237,
    "b": "exo"
  },
  {
    "n": "KIC 5522786 b",
    "p": 757.1639,
    "perr": 0.059,
    "b": "exo"
  },
  {
    "n": "KIC 5732155 b",
    "p": 644.1685,
    "perr": 0.014,
    "b": "exo"
  },
  {
    "n": "KIC 6372194 b",
    "p": 281.5848,
    "perr": 0.0037,
    "b": "exo"
  },
  {
    "n": "KIC 6436029 b",
    "p": 505.45,
    "perr": 0.0042,
    "b": "exo"
  },
  {
    "n": "KIC 7917485 b",
    "p": 840,
    "perr": 22,
    "b": "exo"
  },
  {
    "n": "KIC 8012732 b",
    "p": 431.4681,
    "perr": 0.00358,
    "b": "exo"
  },
  {
    "n": "KIC 9662267 b",
    "p": 466.202,
    "perr": 0.0118,
    "b": "exo"
  },
  {
    "n": "KIC 9704149 b",
    "p": 697.0159,
    "perr": 0.0058,
    "b": "exo"
  },
  {
    "n": "KOI-1299 c",
    "p": 411,
    "perr": 3.2,
    "b": "exo"
  },
  {
    "n": "KOI-415 b",
    "p": 166.78805,
    "perr": 0.00022,
    "b": "exo"
  },
  {
    "n": "KOI-4427.01",
    "p": 147.6606,
    "perr": 0.0011,
    "b": "exo"
  },
  {
    "n": "KOI-5833 b",
    "p": 440.167,
    "perr": 0.01738,
    "b": "exo"
  },
  {
    "n": "KOI-5929 b",
    "p": 466.0001,
    "perr": 0.00799,
    "b": "exo"
  },
  {
    "n": "KOI-620.02",
    "p": 130.194,
    "perr": 0.002,
    "b": "exo"
  },
  {
    "n": "KOI-682 b",
    "p": 562.70945,
    "perr": 0.0411,
    "b": "exo"
  },
  {
    "n": "KOI-771 b",
    "p": 670.6502,
    "perr": 0.01,
    "b": "exo"
  },
  {
    "n": "Kapteyn's c",
    "p": 121.54,
    "perr": 0.25,
    "b": "exo"
  },
  {
    "n": "Kepler-1000 b",
    "p": 120.0181272,
    "perr": 0.0003628,
    "b": "exo"
  },
  {
    "n": "Kepler-1016 c",
    "p": 105.6551369,
    "perr": 0.0005452,
    "b": "exo"
  },
  {
    "n": "Kepler-1020 b",
    "p": 96.9151496,
    "perr": 0.0003632,
    "b": "exo"
  },
  {
    "n": "Kepler-1023 b",
    "p": 62.1387714,
    "perr": 0.0002199,
    "b": "exo"
  },
  {
    "n": "Kepler-1024 b",
    "p": 66.4162133,
    "perr": 0.0003538,
    "b": "exo"
  },
  {
    "n": "Kepler-103 c",
    "p": 179.6133,
    "perr": 0.0047,
    "b": "exo"
  },
  {
    "n": "Kepler-1036 b",
    "p": 122.8808058,
    "perr": 0.000709,
    "b": "exo"
  },
  {
    "n": "Kepler-1038 b",
    "p": 148.4603382,
    "perr": 0.0006894,
    "b": "exo"
  },
  {
    "n": "Kepler-1040 b",
    "p": 201.1214,
    "perr": 0.001945,
    "b": "exo"
  },
  {
    "n": "Kepler-1058 b",
    "p": 110.96546,
    "perr": 0.001146,
    "b": "exo"
  },
  {
    "n": "Kepler-108 c",
    "p": 190.323494,
    "perr": 0.000988,
    "b": "exo"
  },
  {
    "n": "Kepler-1080 b",
    "p": 77.2548396,
    "perr": 0.0003198,
    "b": "exo"
  },
  {
    "n": "Kepler-1085 b",
    "p": 219.3217528,
    "perr": 0.0008946,
    "b": "exo"
  },
  {
    "n": "Kepler-1086 c",
    "p": 161.5163345,
    "perr": 0.0008629,
    "b": "exo"
  },
  {
    "n": "Kepler-1090 b",
    "p": 198.680179,
    "perr": 0.002176,
    "b": "exo"
  },
  {
    "n": "Kepler-1093 c",
    "p": 89.722292,
    "perr": 0.00108,
    "b": "exo"
  },
  {
    "n": "Kepler-1094 b",
    "p": 78.1000231,
    "perr": 0.0006388,
    "b": "exo"
  },
  {
    "n": "Kepler-1097 b",
    "p": 187.747029,
    "perr": 0.001894,
    "b": "exo"
  },
  {
    "n": "Kepler-11 g",
    "p": 118.37774,
    "perr": 0.00112,
    "b": "exo"
  },
  {
    "n": "Kepler-1101 b",
    "p": 81.3151059,
    "perr": 0.0005693,
    "b": "exo"
  },
  {
    "n": "Kepler-111 c",
    "p": 224.784608,
    "perr": 0.000411,
    "b": "exo"
  },
  {
    "n": "Kepler-1126 b",
    "p": 108.593329,
    "perr": 0.001003,
    "b": "exo"
  },
  {
    "n": "Kepler-1128 b",
    "p": 61.6178167,
    "perr": 0.0003337,
    "b": "exo"
  },
  {
    "n": "Kepler-1129 c",
    "p": 76.5369586,
    "perr": 0.0007586,
    "b": "exo"
  },
  {
    "n": "Kepler-1132 b",
    "p": 62.8916228,
    "perr": 0.0004523,
    "b": "exo"
  },
  {
    "n": "Kepler-1135 b",
    "p": 76.957857,
    "perr": 0.0007104,
    "b": "exo"
  },
  {
    "n": "Kepler-1143 c",
    "p": 210.630591,
    "perr": 0.001456,
    "b": "exo"
  },
  {
    "n": "Kepler-1151 b",
    "p": 65.6478424,
    "perr": 0.000401,
    "b": "exo"
  },
  {
    "n": "Kepler-1177 b",
    "p": 106.247547,
    "perr": 0.001822,
    "b": "exo"
  },
  {
    "n": "Kepler-1185 b",
    "p": 104.3518976,
    "perr": 0.0006705,
    "b": "exo"
  },
  {
    "n": "Kepler-1196 b",
    "p": 66.1849031,
    "perr": 0.0004661,
    "b": "exo"
  },
  {
    "n": "Kepler-1204 b",
    "p": 85.7350285,
    "perr": 0.0006373,
    "b": "exo"
  },
  {
    "n": "Kepler-1227 b",
    "p": 94.2887577,
    "perr": 0.0005873,
    "b": "exo"
  },
  {
    "n": "Kepler-1229 b",
    "p": 86.828989,
    "perr": 0.001069,
    "b": "exo"
  },
  {
    "n": "Kepler-1237 b",
    "p": 84.5733226,
    "perr": 0.000648,
    "b": "exo"
  },
  {
    "n": "Kepler-1253 b",
    "p": 68.8861915,
    "perr": 0.000527,
    "b": "exo"
  },
  {
    "n": "Kepler-126 d",
    "p": 100.28208,
    "perr": 0.00041,
    "b": "exo"
  },
  {
    "n": "Kepler-1280 b",
    "p": 66.5579057,
    "perr": 0.0007705,
    "b": "exo"
  },
  {
    "n": "Kepler-129 c",
    "p": 82.20017,
    "perr": 0.00068,
    "b": "exo"
  },
  {
    "n": "Kepler-1294 b",
    "p": 115.6862258,
    "perr": 0.0008445,
    "b": "exo"
  },
  {
    "n": "Kepler-130 d",
    "p": 87.5211,
    "perr": 0.0024,
    "b": "exo"
  },
  {
    "n": "Kepler-1316 b",
    "p": 87.9732136,
    "perr": 0.0005231,
    "b": "exo"
  },
  {
    "n": "Kepler-1318 b",
    "p": 213.257663,
    "perr": 0.001051,
    "b": "exo"
  },
  {
    "n": "Kepler-132 e",
    "p": 110.2869374,
    "perr": 0.000878,
    "b": "exo"
  },
  {
    "n": "Kepler-1333 b",
    "p": 109.6471842,
    "perr": 0.0007077,
    "b": "exo"
  },
  {
    "n": "Kepler-1341 b",
    "p": 132.9968322,
    "perr": 0.0009243,
    "b": "exo"
  },
  {
    "n": "Kepler-1354 b",
    "p": 76.613377,
    "perr": 0.0007773,
    "b": "exo"
  },
  {
    "n": "Kepler-1362 b",
    "p": 136.205626,
    "perr": 0.001278,
    "b": "exo"
  },
  {
    "n": "Kepler-1389 b",
    "p": 99.2530951,
    "perr": 0.0008711,
    "b": "exo"
  },
  {
    "n": "Kepler-139 c",
    "p": 157.072878,
    "perr": 0.00172,
    "b": "exo"
  },
  {
    "n": "Kepler-140 c",
    "p": 91.353282,
    "perr": 0.00137,
    "b": "exo"
  },
  {
    "n": "Kepler-1410 b",
    "p": 60.866168,
    "perr": 0.0005161,
    "b": "exo"
  },
  {
    "n": "Kepler-1411 b",
    "p": 86.1150888,
    "perr": 0.0009728,
    "b": "exo"
  },
  {
    "n": "Kepler-1442 b",
    "p": 81.4162941,
    "perr": 0.0002026,
    "b": "exo"
  },
  {
    "n": "Kepler-1459 b",
    "p": 62.8691611,
    "perr": 0.0009586,
    "b": "exo"
  },
  {
    "n": "Kepler-146 c",
    "p": 76.732171,
    "perr": 0.000609,
    "b": "exo"
  },
  {
    "n": "Kepler-1462 b",
    "p": 65.6488341,
    "perr": 0.0006621,
    "b": "exo"
  },
  {
    "n": "Kepler-1475 b",
    "p": 82.177374,
    "perr": 0.00115,
    "b": "exo"
  },
  {
    "n": "Kepler-1489 b",
    "p": 82.294751,
    "perr": 0.001799,
    "b": "exo"
  },
  {
    "n": "Kepler-149 d",
    "p": 160.018032,
    "perr": 0.001096,
    "b": "exo"
  },
  {
    "n": "Kepler-1490 b",
    "p": 92.4362973,
    "perr": 0.0009042,
    "b": "exo"
  },
  {
    "n": "Kepler-1494 b",
    "p": 91.080482,
    "perr": 0.001769,
    "b": "exo"
  },
  {
    "n": "Kepler-1495 b",
    "p": 85.273256,
    "perr": 0.001954,
    "b": "exo"
  },
  {
    "n": "Kepler-1496 b",
    "p": 64.6588017,
    "perr": 0.00078,
    "b": "exo"
  },
  {
    "n": "Kepler-150 f",
    "p": 637.2093,
    "perr": 0.0169,
    "b": "exo"
  },
  {
    "n": "Kepler-1503 b",
    "p": 96.16987,
    "perr": 0.00118,
    "b": "exo"
  },
  {
    "n": "Kepler-1504 b",
    "p": 82.304003,
    "perr": 0.001593,
    "b": "exo"
  },
  {
    "n": "Kepler-1510 b",
    "p": 84.703921,
    "perr": 0.001896,
    "b": "exo"
  },
  {
    "n": "Kepler-1514 b",
    "p": 217.8317626,
    "perr": 0.0001058,
    "b": "exo"
  },
  {
    "n": "Kepler-1515 b",
    "p": 214.3114164,
    "perr": 0.0001275,
    "b": "exo"
  },
  {
    "n": "Kepler-1519 b",
    "p": 240.7989397,
    "perr": 0.0006117,
    "b": "exo"
  },
  {
    "n": "Kepler-152 c",
    "p": 88.255055,
    "perr": 0.000309,
    "b": "exo"
  },
  {
    "n": "Kepler-1524 b",
    "p": 70.9674603,
    "perr": 0.0001723,
    "b": "exo"
  },
  {
    "n": "Kepler-1527 b",
    "p": 160.129918,
    "perr": 0.001742,
    "b": "exo"
  },
  {
    "n": "Kepler-1533 b",
    "p": 308.5471,
    "perr": 0.002415,
    "b": "exo"
  },
  {
    "n": "Kepler-1535 b",
    "p": 138.9442,
    "perr": 0.001214,
    "b": "exo"
  },
  {
    "n": "Kepler-1536 b",
    "p": 364.758031,
    "perr": 0.00582,
    "b": "exo"
  },
  {
    "n": "Kepler-1538 b",
    "p": 175.138819,
    "perr": 0.002807,
    "b": "exo"
  },
  {
    "n": "Kepler-1539 b",
    "p": 133.3036741,
    "perr": 0.0008843,
    "b": "exo"
  },
  {
    "n": "Kepler-154 c",
    "p": 62.303276,
    "perr": 0.000406,
    "b": "exo"
  },
  {
    "n": "Kepler-1540 b",
    "p": 125.4131177,
    "perr": 0.0004189,
    "b": "exo"
  },
  {
    "n": "Kepler-1544 b",
    "p": 168.811174,
    "perr": 0.001271,
    "b": "exo"
  },
  {
    "n": "Kepler-1545 b",
    "p": 163.692349,
    "perr": 0.001383,
    "b": "exo"
  },
  {
    "n": "Kepler-1548 b",
    "p": 124.828679,
    "perr": 0.001524,
    "b": "exo"
  },
  {
    "n": "Kepler-1549 b",
    "p": 214.886545,
    "perr": 0.003111,
    "b": "exo"
  },
  {
    "n": "Kepler-1550 b",
    "p": 225.582809,
    "perr": 0.003846,
    "b": "exo"
  },
  {
    "n": "Kepler-1552 b",
    "p": 184.771853,
    "perr": 0.001546,
    "b": "exo"
  },
  {
    "n": "Kepler-1554 b",
    "p": 198.088774,
    "perr": 0.002456,
    "b": "exo"
  },
  {
    "n": "Kepler-1562 b",
    "p": 64.2737752,
    "perr": 0.0007141,
    "b": "exo"
  },
  {
    "n": "Kepler-1567 b",
    "p": 153.979578,
    "perr": 0.001785,
    "b": "exo"
  },
  {
    "n": "Kepler-1593 b",
    "p": 174.509835,
    "perr": 0.001852,
    "b": "exo"
  },
  {
    "n": "Kepler-1596 b",
    "p": 66.373379,
    "perr": 0.001476,
    "b": "exo"
  },
  {
    "n": "Kepler-1599 b",
    "p": 122.363553,
    "perr": 0.008968,
    "b": "exo"
  },
  {
    "n": "Kepler-16 (AB) b",
    "p": 228.776,
    "perr": 0.037,
    "b": "exo"
  },
  {
    "n": "Kepler-1600 b",
    "p": 386.370548,
    "perr": 0.008591,
    "b": "exo"
  },
  {
    "n": "Kepler-1605 b",
    "p": 85.7565495,
    "perr": 0.0006161,
    "b": "exo"
  },
  {
    "n": "Kepler-1606 b",
    "p": 196.435224,
    "perr": 0.003935,
    "b": "exo"
  },
  {
    "n": "Kepler-1609 b",
    "p": 114.34219,
    "perr": 0.004097,
    "b": "exo"
  },
  {
    "n": "Kepler-1620 b",
    "p": 101.951829,
    "perr": 0.001572,
    "b": "exo"
  },
  {
    "n": "Kepler-1621 b",
    "p": 92.263714,
    "perr": 0.002385,
    "b": "exo"
  },
  {
    "n": "Kepler-1625 b",
    "p": 287.378949,
    "perr": 0.002983,
    "b": "exo"
  },
  {
    "n": "Kepler-1628 b",
    "p": 76.378033,
    "perr": 0.001833,
    "b": "exo"
  },
  {
    "n": "Kepler-1630 b",
    "p": 509.997402,
    "perr": 0.003256,
    "b": "exo"
  },
  {
    "n": "Kepler-1632 b",
    "p": 448.303558,
    "perr": 0.004164,
    "b": "exo"
  },
  {
    "n": "Kepler-1633 b",
    "p": 186.404271,
    "perr": 0.005886,
    "b": "exo"
  },
  {
    "n": "Kepler-1634 b",
    "p": 374.876239,
    "perr": 0.007107,
    "b": "exo"
  },
  {
    "n": "Kepler-1635 b",
    "p": 469.63111,
    "perr": 0.01246,
    "b": "exo"
  },
  {
    "n": "Kepler-1636 b",
    "p": 425.47785,
    "perr": 0.01122,
    "b": "exo"
  },
  {
    "n": "Kepler-1638 b",
    "p": 259.33683,
    "perr": 0.01303,
    "b": "exo"
  },
  {
    "n": "Kepler-1647 (AB) b",
    "p": 1107.5923,
    "perr": 0.0227,
    "b": "exo"
  },
  {
    "n": "Kepler-167 e",
    "p": 1071.23228,
    "perr": 0.00056,
    "b": "exo"
  },
  {
    "n": "Kepler-169 f",
    "p": 87.090195,
    "perr": 0.000406,
    "b": "exo"
  },
  {
    "n": "Kepler-174 d",
    "p": 247.35373,
    "perr": 0.002001,
    "b": "exo"
  },
  {
    "n": "Kepler-178 d",
    "p": 96.678988,
    "perr": 0.000702,
    "b": "exo"
  },
  {
    "n": "Kepler-186 f",
    "p": 129.9459,
    "perr": 0.0012,
    "b": "exo"
  },
  {
    "n": "Kepler-19 d",
    "p": 62.95,
    "perr": 0.04,
    "b": "exo"
  },
  {
    "n": "Kepler-199 c",
    "p": 67.093408,
    "perr": 0.00019,
    "b": "exo"
  },
  {
    "n": "Kepler-20 d",
    "p": 77.61130017,
    "perr": 0.00012305,
    "b": "exo"
  },
  {
    "n": "Kepler-201 c",
    "p": 151.884058,
    "perr": 0.002014,
    "b": "exo"
  },
  {
    "n": "Kepler-215 e",
    "p": 68.16101,
    "perr": 0.00063,
    "b": "exo"
  },
  {
    "n": "Kepler-218 d",
    "p": 124.5244647,
    "perr": 0.0005822,
    "b": "exo"
  },
  {
    "n": "Kepler-22 b",
    "p": 289.8623,
    "perr": 0.02,
    "b": "exo"
  },
  {
    "n": "Kepler-230 c",
    "p": 91.773242,
    "perr": 0.001618,
    "b": "exo"
  },
  {
    "n": "Kepler-233 c",
    "p": 60.418955,
    "perr": 0.00063,
    "b": "exo"
  },
  {
    "n": "Kepler-25 d",
    "p": 123,
    "perr": 2,
    "b": "exo"
  },
  {
    "n": "Kepler-251 e",
    "p": 99.640161,
    "perr": 0.001074,
    "b": "exo"
  },
  {
    "n": "Kepler-260 c",
    "p": 76.050178,
    "perr": 0.001026,
    "b": "exo"
  },
  {
    "n": "Kepler-264 c",
    "p": 140.101261,
    "perr": 0.003678,
    "b": "exo"
  },
  {
    "n": "Kepler-265 e",
    "p": 67.831024,
    "perr": 0.001396,
    "b": "exo"
  },
  {
    "n": "Kepler-266 c",
    "p": 107.723601,
    "perr": 0.001643,
    "b": "exo"
  },
  {
    "n": "Kepler-268 c",
    "p": 83.446393,
    "perr": 0.000761,
    "b": "exo"
  },
  {
    "n": "Kepler-283 c",
    "p": 92.743711,
    "perr": 0.001413,
    "b": "exo"
  },
  {
    "n": "Kepler-289 c",
    "p": 66.0634,
    "perr": 0.0114,
    "b": "exo"
  },
  {
    "n": "Kepler-289 d",
    "p": 125.8518,
    "perr": 0.0076,
    "b": "exo"
  },
  {
    "n": "Kepler-296 f",
    "p": 63.335879,
    "perr": 0.001292,
    "b": "exo"
  },
  {
    "n": "Kepler-297 c",
    "p": 74.920137,
    "perr": 0.00012,
    "b": "exo"
  },
  {
    "n": "Kepler-298 d",
    "p": 77.473633,
    "perr": 0.000615,
    "b": "exo"
  },
  {
    "n": "Kepler-30 c",
    "p": 60.3231,
    "perr": 0.0002,
    "b": "exo"
  },
  {
    "n": "Kepler-30 d",
    "p": 143.343,
    "perr": 0.009,
    "b": "exo"
  },
  {
    "n": "Kepler-302 c",
    "p": 127.282184,
    "perr": 0.000427,
    "b": "exo"
  },
  {
    "n": "Kepler-309 c",
    "p": 105.356383,
    "perr": 0.000857,
    "b": "exo"
  },
  {
    "n": "Kepler-31 d",
    "p": 87.648901,
    "perr": 0.000801,
    "b": "exo"
  },
  {
    "n": "Kepler-310 d",
    "p": 92.876125,
    "perr": 0.000785,
    "b": "exo"
  },
  {
    "n": "Kepler-315 b",
    "p": 96.101141,
    "perr": 0.000918,
    "b": "exo"
  },
  {
    "n": "Kepler-315 c",
    "p": 265.469335,
    "perr": 0.006223,
    "b": "exo"
  },
  {
    "n": "Kepler-335 c",
    "p": 67.844469,
    "perr": 0.001423,
    "b": "exo"
  },
  {
    "n": "Kepler-34 (AB)  b",
    "p": 288.822,
    "perr": 0.081,
    "b": "exo"
  },
  {
    "n": "Kepler-344 c",
    "p": 125.596809,
    "perr": 0.001728,
    "b": "exo"
  },
  {
    "n": "Kepler-35 (AB) b",
    "p": 131.458,
    "perr": 0.105,
    "b": "exo"
  },
  {
    "n": "Kepler-351 d",
    "p": 142.544247,
    "perr": 0.002303,
    "b": "exo"
  },
  {
    "n": "Kepler-358 c",
    "p": 83.488369,
    "perr": 0.00083,
    "b": "exo"
  },
  {
    "n": "Kepler-359 d",
    "p": 77.095691,
    "perr": 0.001453,
    "b": "exo"
  },
  {
    "n": "Kepler-368 c",
    "p": 72.379334,
    "perr": 0.00137,
    "b": "exo"
  },
  {
    "n": "Kepler-371 c",
    "p": 67.968015,
    "perr": 0.00107,
    "b": "exo"
  },
  {
    "n": "Kepler-379 c",
    "p": 62.784697,
    "perr": 0.000661,
    "b": "exo"
  },
  {
    "n": "Kepler-38 (AB) b",
    "p": 105.595,
    "perr": 0.038,
    "b": "exo"
  },
  {
    "n": "Kepler-397 c",
    "p": 135.498527,
    "perr": 0.000668,
    "b": "exo"
  },
  {
    "n": "Kepler-401 d",
    "p": 184.256405,
    "perr": 0.00317,
    "b": "exo"
  },
  {
    "n": "Kepler-419 b",
    "p": 69.7546,
    "perr": 0.0007,
    "b": "exo"
  },
  {
    "n": "Kepler-419 c",
    "p": 675.47,
    "perr": 0.11,
    "b": "exo"
  },
  {
    "n": "Kepler-421 b",
    "p": 704.1984,
    "perr": 0.0016,
    "b": "exo"
  },
  {
    "n": "Kepler-424 c",
    "p": 223.3,
    "perr": 2.1,
    "b": "exo"
  },
  {
    "n": "Kepler-436 b",
    "p": 64.00205,
    "perr": 0.00053,
    "b": "exo"
  },
  {
    "n": "Kepler-437 b",
    "p": 66.65062,
    "perr": 0.00033,
    "b": "exo"
  },
  {
    "n": "Kepler-439 b",
    "p": 178.1396,
    "perr": 0.0018,
    "b": "exo"
  },
  {
    "n": "Kepler-440 b",
    "p": 101.11141,
    "perr": 0.00068,
    "b": "exo"
  },
  {
    "n": "Kepler-441 b",
    "p": 207.2482,
    "perr": 0.0022,
    "b": "exo"
  },
  {
    "n": "Kepler-442 b",
    "p": 112.3053,
    "perr": 0.0028,
    "b": "exo"
  },
  {
    "n": "Kepler-443 b",
    "p": 177.6693,
    "perr": 0.0031,
    "b": "exo"
  },
  {
    "n": "Kepler-452 b",
    "p": 384.843,
    "perr": 0.007,
    "b": "exo"
  },
  {
    "n": "Kepler-453 (AB) b",
    "p": 240.503,
    "perr": 0.053,
    "b": "exo"
  },
  {
    "n": "Kepler-454 c",
    "p": 523.9,
    "perr": 0.7,
    "b": "exo"
  },
  {
    "n": "Kepler-455 b",
    "p": 1322.3,
    "perr": 386.1,
    "b": "exo"
  },
  {
    "n": "Kepler-456 b",
    "p": 1320.1,
    "perr": 12401.8,
    "b": "exo"
  },
  {
    "n": "Kepler-457 c",
    "p": 75.2,
    "perr": 38.9,
    "b": "exo"
  },
  {
    "n": "Kepler-458 b",
    "p": 572.3847,
    "perr": 0.00583,
    "b": "exo"
  },
  {
    "n": "Kepler-459 b",
    "p": 854.083,
    "perr": 0.01628,
    "b": "exo"
  },
  {
    "n": "Kepler-460 b",
    "p": 440.7813,
    "perr": 0.00563,
    "b": "exo"
  },
  {
    "n": "Kepler-460 c",
    "p": 220.1303357,
    "perr": 0.0006389,
    "b": "exo"
  },
  {
    "n": "Kepler-47 (AB) c",
    "p": 303.148,
    "perr": 0.072,
    "b": "exo"
  },
  {
    "n": "Kepler-48 e",
    "p": 982,
    "perr": 8,
    "b": "exo"
  },
  {
    "n": "Kepler-51 c",
    "p": 85.3128662,
    "perr": 0.00096,
    "b": "exo"
  },
  {
    "n": "Kepler-511 b",
    "p": 296.637865,
    "perr": 0.0004472,
    "b": "exo"
  },
  {
    "n": "Kepler-539 b",
    "p": 125.63243,
    "perr": 0.00071,
    "b": "exo"
  },
  {
    "n": "Kepler-539 c",
    "p": 1000,
    "perr": 1.7976931348623157e+308,
    "b": "exo"
  },
  {
    "n": "Kepler-540 b",
    "p": 172.7049784,
    "perr": 0.0005356,
    "b": "exo"
  },
  {
    "n": "Kepler-549 c",
    "p": 117.040498,
    "perr": 0.001777,
    "b": "exo"
  },
  {
    "n": "Kepler-553 c",
    "p": 328.2399546,
    "perr": 0.0003646,
    "b": "exo"
  },
  {
    "n": "Kepler-56 d",
    "p": 1002,
    "perr": 5,
    "b": "exo"
  },
  {
    "n": "Kepler-591 b",
    "p": 81.1694299,
    "perr": 0.0003199,
    "b": "exo"
  },
  {
    "n": "Kepler-603 c",
    "p": 127.9075774,
    "perr": 0.0004999,
    "b": "exo"
  },
  {
    "n": "Kepler-610 c",
    "p": 151.86392,
    "perr": 0.001118,
    "b": "exo"
  },
  {
    "n": "Kepler-616 c",
    "p": 90.4113556,
    "perr": 0.0004522,
    "b": "exo"
  },
  {
    "n": "Kepler-62 e",
    "p": 122.3874,
    "perr": 0.0008,
    "b": "exo"
  },
  {
    "n": "Kepler-62 f",
    "p": 267.291,
    "perr": 0.005,
    "b": "exo"
  },
  {
    "n": "Kepler-630 b",
    "p": 161.4743937,
    "perr": 0.0009011,
    "b": "exo"
  },
  {
    "n": "Kepler-64 (AB) b",
    "p": 138.506,
    "perr": 0.1,
    "b": "exo"
  },
  {
    "n": "Kepler-68 d",
    "p": 625,
    "perr": 16,
    "b": "exo"
  },
  {
    "n": "Kepler-69 c",
    "p": 242.4613,
    "perr": 0.0064,
    "b": "exo"
  },
  {
    "n": "Kepler-700 b",
    "p": 80.8720639,
    "perr": 0.0001727,
    "b": "exo"
  },
  {
    "n": "Kepler-712 c",
    "p": 226.89047,
    "perr": 0.001096,
    "b": "exo"
  },
  {
    "n": "Kepler-722 c",
    "p": 105.144749,
    "perr": 0.001675,
    "b": "exo"
  },
  {
    "n": "Kepler-767 b",
    "p": 161.5280101,
    "perr": 0.0003086,
    "b": "exo"
  },
  {
    "n": "Kepler-782 b",
    "p": 158.6853308,
    "perr": 0.0004373,
    "b": "exo"
  },
  {
    "n": "Kepler-79 e",
    "p": 81.0659,
    "perr": 0.0013,
    "b": "exo"
  },
  {
    "n": "Kepler-799 b",
    "p": 133.4605235,
    "perr": 0.000253,
    "b": "exo"
  },
  {
    "n": "Kepler-820 b",
    "p": 127.8338098,
    "perr": 0.0003082,
    "b": "exo"
  },
  {
    "n": "Kepler-841 b",
    "p": 124.4198398,
    "perr": 0.000331,
    "b": "exo"
  },
  {
    "n": "Kepler-849 b",
    "p": 394.6244904,
    "perr": 0.0008875,
    "b": "exo"
  },
  {
    "n": "Kepler-86 b",
    "p": 282.5255,
    "perr": 0.001,
    "b": "exo"
  },
  {
    "n": "Kepler-867 b",
    "p": 150.242127,
    "perr": 0.0006047,
    "b": "exo"
  },
  {
    "n": "Kepler-87 b",
    "p": 114.73709,
    "perr": 0.00026,
    "b": "exo"
  },
  {
    "n": "Kepler-87 c",
    "p": 192.363,
    "perr": 0.0074,
    "b": "exo"
  },
  {
    "n": "Kepler-888 b",
    "p": 70.6979061,
    "perr": 0.0003086,
    "b": "exo"
  },
  {
    "n": "Kepler-896 b",
    "p": 144.547396,
    "perr": 0.002274,
    "b": "exo"
  },
  {
    "n": "Kepler-90 e",
    "p": 91.93913,
    "perr": 0.00073,
    "b": "exo"
  },
  {
    "n": "Kepler-90 f",
    "p": 124.9144,
    "perr": 0.0019,
    "b": "exo"
  },
  {
    "n": "Kepler-90 g",
    "p": 210.60697,
    "perr": 0.00043,
    "b": "exo"
  },
  {
    "n": "Kepler-90 h",
    "p": 331.60059,
    "perr": 0.00037,
    "b": "exo"
  },
  {
    "n": "Kepler-903 c",
    "p": 62.9228557,
    "perr": 0.0007353,
    "b": "exo"
  },
  {
    "n": "Kepler-920 c",
    "p": 100.8274113,
    "perr": 0.0007063,
    "b": "exo"
  },
  {
    "n": "Kepler-924 b",
    "p": 61.0370117,
    "perr": 0.0003366,
    "b": "exo"
  },
  {
    "n": "Kepler-930 b",
    "p": 71.4517775,
    "perr": 0.0007523,
    "b": "exo"
  },
  {
    "n": "Kepler-937 b",
    "p": 67.668827,
    "perr": 0.0005833,
    "b": "exo"
  },
  {
    "n": "Kepler-937 c",
    "p": 153.343364,
    "perr": 0.003287,
    "b": "exo"
  },
  {
    "n": "Kepler-94 c",
    "p": 820,
    "perr": 3,
    "b": "exo"
  },
  {
    "n": "Kepler-950 b",
    "p": 98.7180406,
    "perr": 0.0001748,
    "b": "exo"
  },
  {
    "n": "Kepler-952 b",
    "p": 130.3546919,
    "perr": 0.0002069,
    "b": "exo"
  },
  {
    "n": "Kepler-965 b",
    "p": 134.2527298,
    "perr": 0.0005661,
    "b": "exo"
  },
  {
    "n": "Kepler-966 b",
    "p": 99.747622,
    "perr": 0.0004523,
    "b": "exo"
  },
  {
    "n": "Kepler-967 c",
    "p": 198.7112502,
    "perr": 0.0006558,
    "b": "exo"
  },
  {
    "n": "Kepler-976 b",
    "p": 105.9564148,
    "perr": 0.0004626,
    "b": "exo"
  },
  {
    "n": "Kepler-983 b",
    "p": 60.0855082,
    "perr": 0.0002611,
    "b": "exo"
  },
  {
    "n": "Kepler-985 b",
    "p": 116.331901,
    "perr": 0.001381,
    "b": "exo"
  },
  {
    "n": "Kepler-987 b",
    "p": 105.3033148,
    "perr": 0.0004783,
    "b": "exo"
  },
  {
    "n": "Kepler-991 b",
    "p": 82.5342519,
    "perr": 0.0003449,
    "b": "exo"
  },
  {
    "n": "MOA-2009-BLG-266L b",
    "p": 2780,
    "perr": 500,
    "b": "exo"
  },
  {
    "n": "MOA-2009-BLG-387L b",
    "p": 1970,
    "perr": 1.6,
    "b": "exo"
  },
  {
    "n": "NGC 2423 3 b",
    "p": 714.3,
    "perr": 5.3,
    "b": "exo"
  },
  {
    "n": "NGC 4349 No 127 b",
    "p": 677.8,
    "perr": 6.2,
    "b": "exo"
  },
  {
    "n": "NN Ser (AB) c",
    "p": 5660,
    "perr": 165,
    "b": "exo"
  },
  {
    "n": "NN Ser (AB) d",
    "p": 2830,
    "perr": 130,
    "b": "exo"
  },
  {
    "n": "OGLE-2006-109L b",
    "p": 1790,
    "perr": 548,
    "b": "exo"
  },
  {
    "n": "OGLE-2006-109L c",
    "p": 4931,
    "perr": 1750,
    "b": "exo"
  },
  {
    "n": "OGLE-2016-BLG-1190L b",
    "p": 1223.6,
    "perr": 1896,
    "b": "exo"
  },
  {
    "n": "OGLE-GD-ECL-11388 b",
    "p": 3250,
    "perr": 365,
    "b": "exo"
  },
  {
    "n": "PSR 1257 12 c",
    "p": 66.5419,
    "perr": 0.0001,
    "b": "exo"
  },
  {
    "n": "PSR 1257 12 d",
    "p": 98.2114,
    "perr": 0.0002,
    "b": "exo"
  },
  {
    "n": "PSR B0329+54 b",
    "p": 10139.34,
    "perr": 11,
    "b": "exo"
  },
  {
    "n": "Pr 0211 c",
    "p": 5300,
    "perr": 4450,
    "b": "exo"
  },
  {
    "n": "RR Cae b",
    "p": 4350,
    "perr": 37,
    "b": "exo"
  },
  {
    "n": "SAND 364 b",
    "p": 121.71,
    "perr": 0.305,
    "b": "exo"
  },
  {
    "n": "TYC 4282-605-1 b",
    "p": 101.54,
    "perr": 0.05,
    "b": "exo"
  },
  {
    "n": "TYC+1422-614-1 b",
    "p": 198.44,
    "perr": 0.64,
    "b": "exo"
  },
  {
    "n": "TYC+1422-614-1 c",
    "p": 569.2,
    "perr": 2.1,
    "b": "exo"
  },
  {
    "n": "UZ For (AB) d",
    "p": 1900,
    "perr": 90,
    "b": "exo"
  },
  {
    "n": "V391 Peg b",
    "p": 1170,
    "perr": 44,
    "b": "exo"
  },
  {
    "n": "WASP-41 c",
    "p": 421,
    "perr": 2,
    "b": "exo"
  },
  {
    "n": "WASP-47 c",
    "p": 596,
    "perr": 2,
    "b": "exo"
  },
  {
    "n": "WASP-53 c",
    "p": 2840,
    "perr": 1.7976931348623157e+308,
    "b": "exo"
  },
  {
    "n": "WASP-81 c",
    "p": 1297,
    "perr": 8.1,
    "b": "exo"
  },
  {
    "n": "WISE 1217+16 A b",
    "p": 47400,
    "perr": 80000,
    "b": "exo"
  },
  {
    "n": "WISE 1711+3500 b",
    "p": 125000,
    "perr": 29000,
    "b": "exo"
  },
  {
    "n": "WISE J0720-0846",
    "p": 1388,
    "perr": 1096,
    "b": "exo"
  },
  {
    "n": "Wolf 1061 d",
    "p": 217.21,
    "perr": 0.55,
    "b": "exo"
  },
  {
    "n": "XO-2S c",
    "p": 120.8,
    "perr": 0.34,
    "b": "exo"
  },
  {
    "n": "alf Ari b",
    "p": 380.8,
    "perr": 0.3,
    "b": "exo"
  },
  {
    "n": "beta Cnc b",
    "p": 605.2,
    "perr": 4,
    "b": "exo"
  },
  {
    "n": "beta Pic b",
    "p": 13288,
    "perr": 47,
    "b": "exo"
  },
  {
    "n": "beta Umi b",
    "p": 522.3,
    "perr": 2.7,
    "b": "exo"
  },
  {
    "n": "eps CrB b",
    "p": 417.9,
    "perr": 0.5,
    "b": "exo"
  },
  {
    "n": "eps Eridani b",
    "p": 2502,
    "perr": 10,
    "b": "exo"
  },
  {
    "n": "eps Tau b",
    "p": 594.9,
    "perr": 5.3,
    "b": "exo"
  },
  {
    "n": "eta Cet b",
    "p": 403.5,
    "perr": 1.5,
    "b": "exo"
  },
  {
    "n": "eta Cet c",
    "p": 751.9,
    "perr": 3.8,
    "b": "exo"
  },
  {
    "n": "gamma 1 Leo b",
    "p": 428.5,
    "perr": 1.25,
    "b": "exo"
  },
  {
    "n": "gamma Cephei b",
    "p": 903.3,
    "perr": 1.5,
    "b": "exo"
  },
  {
    "n": "kappa CrB b",
    "p": 1251,
    "perr": 15,
    "b": "exo"
  },
  {
    "n": "ksi Aql b",
    "p": 136.75,
    "perr": 0.25,
    "b": "exo"
  },
  {
    "n": "mu Ara b",
    "p": 643.25,
    "perr": 0.9,
    "b": "exo"
  },
  {
    "n": "mu Ara d",
    "p": 310.55,
    "perr": 0.83,
    "b": "exo"
  },
  {
    "n": "mu Ara e",
    "p": 4205.8,
    "perr": 758.9,
    "b": "exo"
  },
  {
    "n": "mu Leo b",
    "p": 357.8,
    "perr": 1.2,
    "b": "exo"
  },
  {
    "n": "nu Oph b",
    "p": 530.32,
    "perr": 0.35,
    "b": "exo"
  },
  {
    "n": "nu Oph c",
    "p": 3186,
    "perr": 14,
    "b": "exo"
  },
  {
    "n": "ome Ser b",
    "p": 277.02,
    "perr": 0.52,
    "b": "exo"
  },
  {
    "n": "omi CrB b",
    "p": 187.3,
    "perr": 54,
    "b": "exo"
  },
  {
    "n": "omi UMa b",
    "p": 1630,
    "perr": 35,
    "b": "exo"
  },
  {
    "n": "sig Per b",
    "p": 579.8,
    "perr": 2.4,
    "b": "exo"
  },
  {
    "n": "tau Cet e",
    "p": 162.87,
    "perr": 1.08,
    "b": "exo"
  },
  {
    "n": "tau Cet f",
    "p": 636.13,
    "perr": 11.7,
    "b": "exo"
  },
  {
    "n": "tau Gem b",
    "p": 305.5,
    "perr": 0.1,
    "b": "exo"
  },
  {
    "n": "ups And c",
    "p": 240.937,
    "perr": 0.06,
    "b": "exo"
  },
  {
    "n": "ups And d",
    "p": 1281.439,
    "perr": 2,
    "b": "exo"
  },
  {
    "n": "ups And e",
    "p": 3848.86,
    "perr": 0.74,
    "b": "exo"
  }
]